tips/__init__.py
tips/admin.py
tips/migrations/0001_initial.py
tips/migrations/0002_auto_20160610_1025.py
tips/migrations/0003_auto_20160610_1537.py
tips/migrations/0004_tipofday_groups.py
tips/migrations/0005_auto_20170124_1441.py
tips/migrations/0006_auto_20180122_2128.py
tips/migrations/__init__.py
tips/models.py
tips/serializers.py
tips/static/tips/js/tips.js
tips/static/tips/js/tips.min.js
tips/templates/tips/base.html
tips/templates/tips/tips.html
tips/urls.py
tips/views.py
django_tips-0.8.2.dist-info/LICENSE
django_tips-0.8.2.dist-info/WHEEL
django_tips-0.8.2.dist-info/METADATA
django_tips-0.8.2.dist-info/RECORD
