Metadata-Version: 2.1
Name: django-tips
Version: 0.8.2
Summary: Show tip of the day cards on your site.
Home-page: https://github.com/trojsten/django-tips
License: BSD-3-Clause
Author: Michal Hozza
Author-email: mhozza@gmail.com
Requires-Python: >=3.5,<4.0
Classifier: Development Status :: 3 - Alpha
Classifier: Framework :: Django
Classifier: Framework :: Django :: 2.0
Classifier: Intended Audience :: Developers
Classifier: License :: OSI Approved :: BSD License
Classifier: Natural Language :: English
Classifier: Programming Language :: Python :: 3
Classifier: Programming Language :: Python :: 3.5
Classifier: Programming Language :: Python :: 3.6
Classifier: Programming Language :: Python :: 3.7
Requires-Dist: django (>=2.0,<3.0)
Requires-Dist: djangorestframework (>=3.10)
Requires-Dist: markdown (>=2.6)
Project-URL: Repository, https://github.com/trojsten/django-tips
